{
    "last_check": "2026-04-27T00:48:32Z",
    "mosques": {
        "alnoor": {
            "version": "2024.04.26",
            "url": "https://raw.githubusercontent.com/ahmednabulsi/weekly-scraper/refs/heads/main/alnoor.json"
        },
        "mca": {
            "version": "2024.04.21",
            "url": "https://raw.githubusercontent.com/ahmednabulsi/weekly-scraper/refs/heads/main/mca.json"
        },
        "bosni": {
            "version": "2024.04.25",
            "url": "https://raw.githubusercontent.com/ahmednabulsi/weekly-scraper/refs/heads/main/bosni.json"
        },
        "Yaseen Belmont Masjid": {
            "version": "2026.04.25",
            "url": "https://raw.githubusercontent.com/ahmednabulsi/weekly-scraper/refs/heads/main/Yaseen%20Belmont%20Masjid.json"
        },
        "Yaseen Burlingame Center": {
            "version": "2026.04.25",
            "url": "https://raw.githubusercontent.com/ahmednabulsi/weekly-scraper/refs/heads/main/Yaseen%20Burlingame%20Center.json"
        },
        "SVIC": {
            "version": "2026.04.27",
            "url": "https://raw.githubusercontent.com/ahmednabulsi/weekly-scraper/refs/heads/main/SVIC.json"
        }
    }
}